{
    "name": "Sarkareth",
    "drops": [
        {
            "name": "Beacon to the Beyond",
            "id": 203963
        },
        {
            "name": "Erethos, the Empty Promise",
            "id": 202565
        },
        {
            "name": "Voice of the Silent Star",
            "id": 204465
        },
        {
            "name": "Fang of the Sundered Flame",
            "id": 202564
        },
        {
            "name": "Oblivion's Immortal Coil",
            "id": 204399
        },
        {
            "name": "Bonds of Desperate Ascension",
            "id": 204390
        },
        {
            "name": "Sarkareth's Abyssal Embrace",
            "id": 202599
        },
        {
            "name": "Crechebound Soldier's Boots",
            "id": 204424
        },
        {
            "name": "Scalecommander's Ebon Schynbalds",
            "id": 202584
        },
        {
            "name": "Coattails of the Rightful Heir",
            "id": 202585
        },
        {
            "name": "Oathbreaker's Obsessive Gauntlets",
            "id": 202587
        }
    ]
}


